README.md
setup.py
datalite3/__init__.py
datalite3/commons.py
datalite3/constraints.py
datalite3/decorator.py
datalite3/fetch.py
datalite3/mass_actions.py
datalite3/migrations.py
datalite3.egg-info/PKG-INFO
datalite3.egg-info/SOURCES.txt
datalite3.egg-info/dependency_links.txt
datalite3.egg-info/top_level.txt
test/__init__.py
test/commons.py
test/sandbox.py
test/tests_auto_commit.py
test/tests_basics.py
test/tests_constraints.py
test/tests_fetch.py
test/tests_mass_insert.py
test/tests_migration.py
test/tests_pagination.py
test/tests_table_name.py