Metadata-Version: 2.1
Name: datalite3
Version: 1.0.1
Summary: A small package that binds dataclasses to an sqlite3 database
Home-page: https://github.com/afdaniele/datalite3
Author: Andrea F. Daniele
Author-email: afdaniele@ttic.edu
License: UNKNOWN
Platform: UNKNOWN
Classifier: Programming Language :: Python :: 3.6
Classifier: License :: OSI Approved :: MIT License
Classifier: Operating System :: OS Independent
Requires-Python: >=3.6
